tird/__init__.py
tird/tird.py
tird-0.22.0.dist-info/METADATA
tird-0.22.0.dist-info/WHEEL
tird-0.22.0.dist-info/entry_points.txt
tird-0.22.0.dist-info/top_level.txt
tird-0.22.0.dist-info/RECORD
