Metadata-Version: 2.4
Name: tird
Version: 0.22.0
Summary: A file encryption tool focused on minimizing metadata and hiding encrypted data
Maintainer-email: Alexey Avramov <hakavlad@gmail.com>
License-Expression: 0BSD
Project-URL: Bug Tracker, https://github.com/hakavlad/tird/issues
Project-URL: Discussions, https://github.com/hakavlad/tird/discussions
Project-URL: Documentation, https://github.com/hakavlad/tird/blob/main/README.md
Project-URL: Homepage, https://github.com/hakavlad/tird
Project-URL: Repository, https://github.com/hakavlad/tird
Keywords: encryption,file-encryption,hiding,data-hiding,plausible-deniability,deniable-encryption,purb,time-lock,undetectable,stealth,steganography
Classifier: Development Status :: 3 - Alpha
Classifier: Environment :: Console
Classifier: Intended Audience :: End Users/Desktop
Classifier: Operating System :: OS Independent
Classifier: Programming Language :: Python :: 3
Classifier: Topic :: Security
Classifier: Topic :: Security :: Cryptography
Classifier: Topic :: Utilities
Classifier: Typing :: Typed
Requires-Python: >=3.9.2
Requires-Dist: cryptography>=2.1
Requires-Dist: pynacl>=1.2.0
Requires-Dist: colorama>=0.4.6; sys_platform == "win32"
